bond_api/__init__.py
bond_api/action.py
bond_api/bond.py
bond_api/bpup.py
bond_api/device_type.py
bond_api-0.1.18.dist-info/LICENSE
bond_api-0.1.18.dist-info/METADATA
bond_api-0.1.18.dist-info/WHEEL
bond_api-0.1.18.dist-info/top_level.txt
bond_api-0.1.18.dist-info/RECORD
