Metadata-Version: 2.1
Name: bond-api
Version: 0.1.18
Summary: Asynchronous Python wrapper library over Bond Local API
Home-page: https://github.com/prystupa/bond-api
Author: Eugene Prystupa
Author-email: eugene.prystupa@gmail.com
License: MIT
Keywords: bond local api async
Platform: UNKNOWN
Classifier: Intended Audience :: Developers
Classifier: License :: OSI Approved :: MIT License
Classifier: Operating System :: OS Independent
Classifier: Programming Language :: Python :: 3.7
Classifier: Topic :: Home Automation
License-File: LICENSE
Requires-Dist: aiohttp (>=3.6.1)
